existenz_api_fetcher/__init__.py
existenz_api_fetcher/hydro.py
existenz_api_fetcher/locations.py
existenz_api_fetcher/meteo.py
existenz_api_fetcher/pipelines.py
tests/__init__.py
tests/test_hydro.py
tests/test_meteo.py
tests/test_pipelines.py
existenz_api_fetcher-0.1.4.dist-info/LICENSE.txt
existenz_api_fetcher-0.1.4.dist-info/METADATA
existenz_api_fetcher-0.1.4.dist-info/WHEEL
existenz_api_fetcher-0.1.4.dist-info/top_level.txt
existenz_api_fetcher-0.1.4.dist-info/RECORD
