Metadata-Version: 2.1
Name: existenz_api_fetcher
Version: 0.1.4
Summary: Easily fetch swiss weather and hydrological data from the Existenz API
Home-page: https://github.com/Lilian1510/ExistenzAPIFetcher/
Author: Lilian Lonla
Author-email: Lilian Lonla <lilianlonla15@gmail.com>
Project-URL: Homepage, https://github.com/Lilian1510/ExistenzAPIFetcher/
Classifier: Programming Language :: Python :: 3
Classifier: License :: OSI Approved :: MIT License
Classifier: Operating System :: OS Independent
Requires-Python: >=3.7
License-File: LICENSE.txt
